chords2midi/__init__.py
chords2midi/c2m.py
chords2midi-0.7.0.dist-info/METADATA
chords2midi-0.7.0.dist-info/RECORD
chords2midi-0.7.0.dist-info/WHEEL
chords2midi-0.7.0.dist-info/entry_points.txt
chords2midi-0.7.0.dist-info/top_level.txt
