Metadata-Version: 2.1
Name: chords2midi
Version: 0.7.0
Summary: Create MIDI files from chord progressions
Home-page: https://github.com/Miserlou/chords2midi
Author: Rich Jones
Author-email: rich@openwatch.net
License: MIT License
Platform: UNKNOWN
Classifier: Environment :: Console
Classifier: License :: OSI Approved :: Apache Software License
Classifier: Operating System :: OS Independent
Classifier: Programming Language :: Python
Classifier: Programming Language :: Python :: 2.7
Classifier: Topic :: Internet :: WWW/HTTP
Classifier: Topic :: Internet :: WWW/HTTP :: Dynamic Content
Requires-Dist: MIDIUtil (==1.2.1)
Requires-Dist: mingus (==0.5.1)
Requires-Dist: pychord (==0.3.1)
